honeybees/__init__.py
honeybees/agents.py
honeybees/area.py
honeybees/argparse.py
honeybees/artists.py
honeybees/model.py
honeybees/reporter.py
honeybees/library/__init__.py
honeybees/library/geohash.py
honeybees/library/helpers.py
honeybees/library/mapIO.py
honeybees/library/math.py
honeybees/library/neighbors.py
honeybees/library/raster.py
honeybees/visualization/ModularVisualization.py
honeybees/visualization/UserParam.py
honeybees/visualization/__init__.py
honeybees/visualization/canvas.py
honeybees/visualization/modules/ChartVisualization.py
honeybees/visualization/modules/__init__.py
honeybees/visualization/templates/favicon.ico
honeybees/visualization/templates/modular_template.html
honeybees/visualization/templates/css/bootstrap-slider.css
honeybees/visualization/templates/css/bootstrap-switch.css
honeybees/visualization/templates/css/bootstrap-theme.css
honeybees/visualization/templates/css/bootstrap-theme.css.map
honeybees/visualization/templates/css/bootstrap.css
honeybees/visualization/templates/css/bootstrap.css.map
honeybees/visualization/templates/css/visualization.css
honeybees/visualization/templates/fonts/glyphicons-halflings-regular.eot
honeybees/visualization/templates/fonts/glyphicons-halflings-regular.svg
honeybees/visualization/templates/fonts/glyphicons-halflings-regular.ttf
honeybees/visualization/templates/fonts/glyphicons-halflings-regular.woff
honeybees/visualization/templates/fonts/glyphicons-halflings-regular.woff2
honeybees/visualization/templates/js/Chart.min.js
honeybees/visualization/templates/js/ChartModule.js
honeybees/visualization/templates/js/bootstrap-slider.js
honeybees/visualization/templates/js/bootstrap-switch.js
honeybees/visualization/templates/js/bootstrap.js
honeybees/visualization/templates/js/canvas.js
honeybees/visualization/templates/js/d3.min.js
honeybees/visualization/templates/js/jquery.min.js
honeybees/visualization/templates/js/runcontrol.js
honeybees-1.2.0.dist-info/licenses/LICENSE
honeybees-1.2.0.dist-info/WHEEL
honeybees-1.2.0.dist-info/METADATA
honeybees-1.2.0.dist-info/RECORD
