Metadata-Version: 2.4
Name: honeybees
Version: 1.2.0
Summary: Honeybees is an agent-based modelling framework targeted at large-scale agent-based models.
Author-email: Jens de Bruijn <j.a.debruijn@outlook.com>
Requires-Python: >=3.10
Classifier: Development Status :: 4 - Beta
Classifier: Intended Audience :: Developers
Classifier: Intended Audience :: Science/Research
Classifier: Topic :: Scientific/Engineering
Classifier: License :: OSI Approved :: GNU General Public License v3 (GPLv3)
Classifier: Programming Language :: Python :: 3
License-File: LICENSE
Requires-Dist: netcdf4
Requires-Dist: pandas
Requires-Dist: openpyxl
Requires-Dist: geopandas
Requires-Dist: numpy
Requires-Dist: numba>=0.61.0
Requires-Dist: tornado
Requires-Dist: python-dateutil
Requires-Dist: rasterio
Requires-Dist: pyyaml
Requires-Dist: matplotlib
Requires-Dist: xarray
Requires-Dist: rioxarray
Requires-Dist: zarr>=3.0.5
Requires-Dist: matplotlib ; extra == "dev"
Requires-Dist: pytest ; extra == "dev"
Requires-Dist: pytest-plt ; extra == "dev"
Requires-Dist: pytest-benchmark ; extra == "dev"
Requires-Dist: cartopy ; extra == "dev"
Requires-Dist: ruff ; extra == "dev"
Requires-Dist: sphinx ; extra == "docs"
Requires-Dist: sphinx_rtd_theme ; extra == "docs"
Requires-Dist: sphinx-autodoc-typehints ; extra == "docs"
Requires-Dist: sphinxcontrib-autoprogram ; extra == "docs"
Requires-Dist: cartopy ; extra == "plotting"
Provides-Extra: dev
Provides-Extra: docs
Provides-Extra: plotting
